[
  {
    "name": "Sunshine Tech Solutions LLC",
    "state": "FL",
    "entity_number": "L2400100000",
    "registration_date": "2026-01-20",
    "entity_type": "Limited Liability Company",
    "status": "Active",
    "registered_agent": "Registered Agent Services 1",
    "address": "Miami, FL",
    "scraped_at": "2026-02-17T02:29:04.088067",
    "source": "sample_data"
  },
  {
    "name": "Coastal Marketing Group Inc",
    "state": "FL",
    "entity_number": "L2400100001",
    "registration_date": "2026-01-19",
    "entity_type": "Corporation",
    "status": "Active",
    "registered_agent": "Registered Agent Services 2",
    "address": "Orlando, FL",
    "scraped_at": "2026-02-17T02:29:04.088085",
    "source": "sample_data"
  },
  {
    "name": "Miami Consulting Services LLC",
    "state": "FL",
    "entity_number": "L2400100002",
    "registration_date": "2026-02-01",
    "entity_type": "Limited Liability Company",
    "status": "Active",
    "registered_agent": "Registered Agent Services 3",
    "address": "Orlando, FL",
    "scraped_at": "2026-02-17T02:29:04.088093",
    "source": "sample_data"
  },
  {
    "name": "Tampa Bay Ventures Corp",
    "state": "FL",
    "entity_number": "L2400100003",
    "registration_date": "2026-02-12",
    "entity_type": "Corporation",
    "status": "Active",
    "registered_agent": "Registered Agent Services 4",
    "address": "Tampa, FL",
    "scraped_at": "2026-02-17T02:29:04.088100",
    "source": "sample_data"
  },
  {
    "name": "Orlando Innovation Labs LLC",
    "state": "FL",
    "entity_number": "L2400100004",
    "registration_date": "2026-02-08",
    "entity_type": "Limited Liability Company",
    "status": "Active",
    "registered_agent": "Registered Agent Services 5",
    "address": "Miami, FL",
    "scraped_at": "2026-02-17T02:29:04.088109",
    "source": "sample_data"
  },
  {
    "name": "Jacksonville Digital Media Inc",
    "state": "FL",
    "entity_number": "L2400100005",
    "registration_date": "2026-02-06",
    "entity_type": "Corporation",
    "status": "Active",
    "registered_agent": "Registered Agent Services 6",
    "address": "Tampa, FL",
    "scraped_at": "2026-02-17T02:29:04.088115",
    "source": "sample_data"
  },
  {
    "name": "Palm Beach Capital LLC",
    "state": "FL",
    "entity_number": "L2400100006",
    "registration_date": "2026-02-12",
    "entity_type": "Limited Liability Company",
    "status": "Active",
    "registered_agent": "Registered Agent Services 7",
    "address": "Jacksonville, FL",
    "scraped_at": "2026-02-17T02:29:04.088120",
    "source": "sample_data"
  },
  {
    "name": "Fort Lauderdale Holdings Corp",
    "state": "FL",
    "entity_number": "L2400100007",
    "registration_date": "2026-02-16",
    "entity_type": "Corporation",
    "status": "Active",
    "registered_agent": "Registered Agent Services 8",
    "address": "Orlando, FL",
    "scraped_at": "2026-02-17T02:29:04.088125",
    "source": "sample_data"
  },
  {
    "name": "Naples Investment Group LLC",
    "state": "FL",
    "entity_number": "L2400100008",
    "registration_date": "2026-01-30",
    "entity_type": "Limited Liability Company",
    "status": "Active",
    "registered_agent": "Registered Agent Services 9",
    "address": "Miami, FL",
    "scraped_at": "2026-02-17T02:29:04.088130",
    "source": "sample_data"
  },
  {
    "name": "Clearwater Technologies Inc",
    "state": "FL",
    "entity_number": "L2400100009",
    "registration_date": "2026-02-06",
    "entity_type": "Corporation",
    "status": "Active",
    "registered_agent": "Registered Agent Services 10",
    "address": "Tampa, FL",
    "scraped_at": "2026-02-17T02:29:04.088138",
    "source": "sample_data"
  },
  {
    "name": "Boca Raton Enterprises LLC",
    "state": "FL",
    "entity_number": "L2400100010",
    "registration_date": "2026-01-27",
    "entity_type": "Limited Liability Company",
    "status": "Active",
    "registered_agent": "Registered Agent Services 11",
    "address": "Jacksonville, FL",
    "scraped_at": "2026-02-17T02:29:04.088149",
    "source": "sample_data"
  },
  {
    "name": "Sarasota Business Solutions Inc",
    "state": "FL",
    "entity_number": "L2400100011",
    "registration_date": "2026-01-24",
    "entity_type": "Corporation",
    "status": "Active",
    "registered_agent": "Registered Agent Services 12",
    "address": "Jacksonville, FL",
    "scraped_at": "2026-02-17T02:29:04.088157",
    "source": "sample_data"
  },
  {
    "name": "Port St Lucie Consulting LLC",
    "state": "FL",
    "entity_number": "L2400100012",
    "registration_date": "2026-02-03",
    "entity_type": "Limited Liability Company",
    "status": "Active",
    "registered_agent": "Registered Agent Services 13",
    "address": "Jacksonville, FL",
    "scraped_at": "2026-02-17T02:29:04.088165",
    "source": "sample_data"
  },
  {
    "name": "Tallahassee Services Corp",
    "state": "FL",
    "entity_number": "L2400100013",
    "registration_date": "2026-01-27",
    "entity_type": "Corporation",
    "status": "Active",
    "registered_agent": "Registered Agent Services 14",
    "address": "Jacksonville, FL",
    "scraped_at": "2026-02-17T02:29:04.088173",
    "source": "sample_data"
  },
  {
    "name": "Pensacola Ventures LLC",
    "state": "FL",
    "entity_number": "L2400100014",
    "registration_date": "2026-01-25",
    "entity_type": "Limited Liability Company",
    "status": "Active",
    "registered_agent": "Registered Agent Services 15",
    "address": "Jacksonville, FL",
    "scraped_at": "2026-02-17T02:29:04.088178",
    "source": "sample_data"
  }
]