[
  {
    "name": "Mid-Atlantic Healthcare Systems LLP",
    "state": "DE",
    "entity_number": "100-000-014",
    "registration_date": "2026-02-18",
    "entity_type": "Limited Liability Partnership",
    "status": "Active",
    "registered_agent": "Delaware Registered Agent #736",
    "address": "Milton, DE 19877",
    "scraped_at": "2026-02-18T00:37:58.143319",
    "source": "scheduled_generation",
    "generator_run": 1,
    "business_id": "2d1f5ef7917f"
  },
  {
    "name": "Dover Logistics Inc",
    "state": "DE",
    "entity_number": "100-000-000",
    "registration_date": "2026-02-18",
    "entity_type": "Corporation",
    "status": "Active",
    "registered_agent": "Delaware Registered Agent #280",
    "address": "Camden, DE 19839",
    "scraped_at": "2026-02-18T00:37:58.143105",
    "source": "scheduled_generation",
    "generator_run": 1,
    "business_id": "c32100d79732"
  },
  {
    "name": "Smyrna Associates LLC",
    "state": "DE",
    "entity_number": "100-000-019",
    "registration_date": "2026-02-16",
    "entity_type": "Limited Liability Company",
    "status": "Active",
    "registered_agent": "Delaware Registered Agent #693",
    "address": "Millsboro, DE 19832",
    "scraped_at": "2026-02-18T00:37:58.143378",
    "source": "scheduled_generation",
    "generator_run": 1,
    "business_id": "ba46b3f52f9c"
  },
  {
    "name": "New Castle Consulting LLC",
    "state": "DE",
    "entity_number": "100-000-016",
    "registration_date": "2026-02-16",
    "entity_type": "Limited Liability Company",
    "status": "Active",
    "registered_agent": "Delaware Registered Agent #692",
    "address": "Georgetown, DE 19966",
    "scraped_at": "2026-02-18T00:37:58.143343",
    "source": "scheduled_generation",
    "generator_run": 1,
    "business_id": "530aabc92802"
  },
  {
    "name": "Wilmington Construction LLC",
    "state": "DE",
    "entity_number": "100-000-004",
    "registration_date": "2026-02-16",
    "entity_type": "Limited Liability Company",
    "status": "Active",
    "registered_agent": "Delaware Registered Agent #199",
    "address": "Milton, DE 19731",
    "scraped_at": "2026-02-18T00:37:58.143180",
    "source": "scheduled_generation",
    "generator_run": 1,
    "business_id": "ab61b73a82c0"
  },
  {
    "name": "New Castle Retail LLC",
    "state": "DE",
    "entity_number": "100-000-002",
    "registration_date": "2026-02-16",
    "entity_type": "Limited Liability Company",
    "status": "Active",
    "registered_agent": "Delaware Registered Agent #495",
    "address": "Harrington, DE 19978",
    "scraped_at": "2026-02-18T00:37:58.143151",
    "source": "scheduled_generation",
    "generator_run": 1,
    "business_id": "9f531c5850ac"
  },
  {
    "name": "Peninsula Networks LLP",
    "state": "DE",
    "entity_number": "100-000-005",
    "registration_date": "2026-02-14",
    "entity_type": "Limited Liability Partnership",
    "status": "Active",
    "registered_agent": "Delaware Registered Agent #904",
    "address": "Smyrna, DE 19919",
    "scraped_at": "2026-02-18T00:37:58.143196",
    "source": "scheduled_generation",
    "generator_run": 1,
    "business_id": "fc264aa43ea8"
  },
  {
    "name": "Mid-Atlantic Services LP",
    "state": "DE",
    "entity_number": "100-000-001",
    "registration_date": "2026-02-13",
    "entity_type": "Limited Partnership",
    "status": "Active",
    "registered_agent": "Delaware Registered Agent #774",
    "address": "Laurel, DE 19925",
    "scraped_at": "2026-02-18T00:37:58.143132",
    "source": "scheduled_generation",
    "generator_run": 1,
    "business_id": "b5c363e24623"
  },
  {
    "name": "Selbyville Construction Corp",
    "state": "DE",
    "entity_number": "100-000-018",
    "registration_date": "2026-02-12",
    "entity_type": "Corporation",
    "status": "Active",
    "registered_agent": "Delaware Registered Agent #326",
    "address": "Middletown, DE 19917",
    "scraped_at": "2026-02-18T00:37:58.143367",
    "source": "scheduled_generation",
    "generator_run": 1,
    "business_id": "eab0bccde006"
  },
  {
    "name": "Diamond Properties PC",
    "state": "DE",
    "entity_number": "100-000-012",
    "registration_date": "2026-02-11",
    "entity_type": "Professional Corporation",
    "status": "Active",
    "registered_agent": "Delaware Registered Agent #410",
    "address": "Clayton, DE 19941",
    "scraped_at": "2026-02-18T00:37:58.143295",
    "source": "scheduled_generation",
    "generator_run": 1,
    "business_id": "c2aa101b73a8"
  },
  {
    "name": "Diamond Enterprises Inc",
    "state": "DE",
    "entity_number": "100-000-015",
    "registration_date": "2026-02-09",
    "entity_type": "Corporation",
    "status": "Active",
    "registered_agent": "Delaware Registered Agent #496",
    "address": "Georgetown, DE 19790",
    "scraped_at": "2026-02-18T00:37:58.143332",
    "source": "scheduled_generation",
    "generator_run": 1,
    "business_id": "5528a3be02fb"
  },
  {
    "name": "Wilmington Healthcare Corp",
    "state": "DE",
    "entity_number": "100-000-003",
    "registration_date": "2026-02-09",
    "entity_type": "Corporation",
    "status": "Active",
    "registered_agent": "Delaware Registered Agent #165",
    "address": "Dover, DE 19824",
    "scraped_at": "2026-02-18T00:37:58.143166",
    "source": "scheduled_generation",
    "generator_run": 1,
    "business_id": "21d81df597e6"
  },
  {
    "name": "Diamond State Technology Holdings LLP",
    "state": "DE",
    "entity_number": "100-000-017",
    "registration_date": "2026-02-08",
    "entity_type": "Limited Liability Partnership",
    "status": "Active",
    "registered_agent": "Delaware Registered Agent #303",
    "address": "Camden, DE 19713",
    "scraped_at": "2026-02-18T00:37:58.143355",
    "source": "scheduled_generation",
    "generator_run": 1,
    "business_id": "9e646e9c6fa4"
  },
  {
    "name": "Georgetown Group PC",
    "state": "DE",
    "entity_number": "100-000-013",
    "registration_date": "2026-02-07",
    "entity_type": "Professional Corporation",
    "status": "Active",
    "registered_agent": "Delaware Registered Agent #888",
    "address": "Laurel, DE 19854",
    "scraped_at": "2026-02-18T00:37:58.143307",
    "source": "scheduled_generation",
    "generator_run": 1,
    "business_id": "20f00a74f11c"
  },
  {
    "name": "First State Logistics Networks LLP",
    "state": "DE",
    "entity_number": "100-000-010",
    "registration_date": "2026-02-07",
    "entity_type": "Limited Liability Partnership",
    "status": "Active",
    "registered_agent": "Delaware Registered Agent #945",
    "address": "Middletown, DE 19765",
    "scraped_at": "2026-02-18T00:37:58.143270",
    "source": "scheduled_generation",
    "generator_run": 1,
    "business_id": "d00d5aafa54e"
  },
  {
    "name": "First State Healthcare Resources LLC",
    "state": "DE",
    "entity_number": "100-000-011",
    "registration_date": "2026-01-31",
    "entity_type": "Limited Liability Company",
    "status": "Active",
    "registered_agent": "Delaware Registered Agent #694",
    "address": "Milton, DE 19743",
    "scraped_at": "2026-02-18T00:37:58.143284",
    "source": "scheduled_generation",
    "generator_run": 1,
    "business_id": "134d201dbef3"
  },
  {
    "name": "Diamond State Development Corp",
    "state": "DE",
    "entity_number": "100-000-009",
    "registration_date": "2026-01-29",
    "entity_type": "Corporation",
    "status": "Active",
    "registered_agent": "Delaware Registered Agent #305",
    "address": "Milton, DE 19938",
    "scraped_at": "2026-02-18T00:37:58.143257",
    "source": "scheduled_generation",
    "generator_run": 1,
    "business_id": "fe0e248a40ab"
  },
  {
    "name": "Seaford Development LLC",
    "state": "DE",
    "entity_number": "100-000-006",
    "registration_date": "2026-01-24",
    "entity_type": "Limited Liability Company",
    "status": "Active",
    "registered_agent": "Delaware Registered Agent #300",
    "address": "Harrington, DE 19980",
    "scraped_at": "2026-02-18T00:37:58.143209",
    "source": "scheduled_generation",
    "generator_run": 1,
    "business_id": "ce6b321876f6"
  },
  {
    "name": "Delmarva Government Development LLC",
    "state": "DE",
    "entity_number": "100-000-007",
    "registration_date": "2026-01-20",
    "entity_type": "Limited Liability Company",
    "status": "Active",
    "registered_agent": "Delaware Registered Agent #481",
    "address": "Milton, DE 19881",
    "scraped_at": "2026-02-18T00:37:58.143230",
    "source": "scheduled_generation",
    "generator_run": 1,
    "business_id": "a54ccd233836"
  },
  {
    "name": "Peninsula Ventures PC",
    "state": "DE",
    "entity_number": "100-000-008",
    "registration_date": "2026-01-19",
    "entity_type": "Professional Corporation",
    "status": "Active",
    "registered_agent": "Delaware Registered Agent #959",
    "address": "Dover, DE 19714",
    "scraped_at": "2026-02-18T00:37:58.143244",
    "source": "scheduled_generation",
    "generator_run": 1,
    "business_id": "463ceaacb569"
  }
]